Mathm/__init__.py
Mathm/aream/__init__.py
Mathm/calculatorm/__init__.py
Mathm-0.1.dist-info/LICENCE.txt
Mathm-0.1.dist-info/METADATA
Mathm-0.1.dist-info/WHEEL
Mathm-0.1.dist-info/top_level.txt
Mathm-0.1.dist-info/RECORD
