Metadata-Version: 2.1
Name: Mathm
Version: 0.1
Summary: Math Module
Author: Salman Mumtaz
Author-email: salmanmumtaz123456@gmail.com
Classifier: Operating System :: Microsoft :: Windows :: Windows 10
Classifier: License :: OSI Approved :: MIT License
Classifier: Programming Language :: Python :: 3
License-File: LICENCE.txt
